torchgmm/__init__.py
torchgmm/base/__init__.py
torchgmm/base/data/__init__.py
torchgmm/base/data/collation.py
torchgmm/base/data/loader.py
torchgmm/base/data/sampler.py
torchgmm/base/data/types.py
torchgmm/base/estimator/__init__.py
torchgmm/base/estimator/_protocols.py
torchgmm/base/estimator/base.py
torchgmm/base/estimator/configurable.py
torchgmm/base/estimator/exception.py
torchgmm/base/estimator/mixins.py
torchgmm/base/nn/__init__.py
torchgmm/base/nn/_protocols.py
torchgmm/base/nn/configurable.py
torchgmm/base/utils/__init__.py
torchgmm/base/utils/generics.py
torchgmm/base/utils/path.py
torchgmm/bayes/__init__.py
torchgmm/bayes/core/__init__.py
torchgmm/bayes/core/_jit.py
torchgmm/bayes/core/normal.py
torchgmm/bayes/core/types.py
torchgmm/bayes/core/utils.py
torchgmm/bayes/gmm/__init__.py
torchgmm/bayes/gmm/estimator.py
torchgmm/bayes/gmm/lightning_module.py
torchgmm/bayes/gmm/metrics.py
torchgmm/bayes/gmm/model.py
torchgmm/bayes/gmm/types.py
torchgmm/clustering/__init__.py
torchgmm/clustering/kmeans/__init__.py
torchgmm/clustering/kmeans/estimator.py
torchgmm/clustering/kmeans/lightning_module.py
torchgmm/clustering/kmeans/metrics.py
torchgmm/clustering/kmeans/model.py
torchgmm/clustering/kmeans/types.py
torchgmm/utils/__init__.py
torchgmm/utils/lightning_module.py
torchgmm-0.1.3.dist-info/METADATA
torchgmm-0.1.3.dist-info/WHEEL
torchgmm-0.1.3.dist-info/licenses/LICENSE
torchgmm-0.1.3.dist-info/RECORD
