Metadata-Version: 2.4
Name: torchgmm
Version: 0.1.3
Summary: Run Gaussian Mixture Models on single or multiple CPUs/GPUs
Project-URL: Documentation, https://torchgmm.readthedocs.io/
Project-URL: Source, https://github.com/CSOgroup/torchgmm
Project-URL: Home-page, https://github.com/CSOgroup/torchgmm
Author: Marco Varrone
Maintainer-email: Marco Varrone <marco.varrone@unil.ch>
License: MIT License
License-File: LICENSE
Requires-Python: <3.14,>=3.8
Requires-Dist: anndata
Requires-Dist: numpy>=1.20.3
Requires-Dist: pytorch-lightning>=2.0.0
Requires-Dist: session-info
Requires-Dist: torch>1.11.0
Requires-Dist: torchmetrics>=0.6
Provides-Extra: dev
Requires-Dist: pre-commit; extra == 'dev'
Requires-Dist: twine>=4.0.2; extra == 'dev'
Provides-Extra: doc
Requires-Dist: docutils!=0.18.*,!=0.19.*,>=0.8; extra == 'doc'
Requires-Dist: ipykernel; extra == 'doc'
Requires-Dist: ipython; extra == 'doc'
Requires-Dist: myst-nb>=1.1.0; extra == 'doc'
Requires-Dist: pandas; extra == 'doc'
Requires-Dist: setuptools; extra == 'doc'
Requires-Dist: sphinx-autodoc-typehints; extra == 'doc'
Requires-Dist: sphinx-book-theme>=1.0.0; extra == 'doc'
Requires-Dist: sphinx-copybutton; extra == 'doc'
Requires-Dist: sphinx>=4; extra == 'doc'
Requires-Dist: sphinxcontrib-bibtex>=1.0.0; extra == 'doc'
Requires-Dist: sphinxext-opengraph; extra == 'doc'
Provides-Extra: test
Requires-Dist: coverage; extra == 'test'
Requires-Dist: flaky; extra == 'test'
Requires-Dist: pytest; extra == 'test'
Requires-Dist: pytest-benchmark; extra == 'test'
Requires-Dist: scikit-learn; extra == 'test'
